subregistry/__init__.py
subregistry/decorator.py
subregistry/subclass_registry.py
subregistry-0.1.1.dist-info/licenses/LICENSE
subregistry-0.1.1.dist-info/METADATA
subregistry-0.1.1.dist-info/WHEEL
subregistry-0.1.1.dist-info/top_level.txt
subregistry-0.1.1.dist-info/RECORD
